eventgraph-0.1.1.dist-info/METADATA
eventgraph-0.1.1.dist-info/WHEEL
eventgraph-0.1.1.dist-info/entry_points.txt
eventgraph-0.1.1.dist-info/licenses/LICENSE
eventgraph/__init__.py
eventgraph/core/__init__.py
eventgraph/core/base.py
eventgraph/core/core.py
eventgraph/dispatcher/__init__.py
eventgraph/dispatcher/base.py
eventgraph/event/__init__.py
eventgraph/event/base.py
eventgraph/event/builtins.py
eventgraph/exceptions.py
eventgraph/executor/__init__.py
eventgraph/executor/base.py
eventgraph/listener/__init__.py
eventgraph/listener/base.py
eventgraph/queue/__init__.py
eventgraph/queue/base.py
eventgraph/source/__init__.py
eventgraph/source/base.py
eventgraph-0.1.1.dist-info/RECORD
