Metadata-Version: 2.1
Name: eventgraph
Version: 0.1.1
Summary: 一个现代的事件系统
Author-Email: luxuncang <luxuncang@qq.com>
License: MIT
Requires-Python: >=3.10
Requires-Dist: typing-tool>=0.1.2
Requires-Dist: mapgraph>=0.2.1
